enavigation/__init__.py
enavigation/_graph.py
enavigation/_simplepathfinder.py
enavigation/py.typed
enavigation-0.1.0.dist-info/METADATA
enavigation-0.1.0.dist-info/WHEEL
enavigation-0.1.0.dist-info/RECORD
