Metadata-Version: 2.1
Name: enavigation
Version: 0.1.0
Summary: Pathfinding and navigation.
Author: Erik Soma
Author-email: stillusingirc@gmail.com
Requires-Python: >=3.12,<4.0
Classifier: Programming Language :: Python :: 3
Classifier: Programming Language :: Python :: 3.12
Requires-Dist: sortedcontainers (>=2.0.0,<3.0.0)
